{"meta":{"code":200,"requestId":"61eaa1429a11ec1e009fedd7"},"notifications":[{"type":"notificationTray","item":{"unreadCount":0}}],"response":{"venue":{"id":"589b75ac18fd2b5565de258b","name":"Temaki - Japanese Street Food","contact":{"phone":"0770385940","formattedPhone":"0770 385 940","facebook":"1728186224060616","facebookUsername":"temakicluj","facebookName":"Temaki"},"location":{"address":"Str. Regele Ferdinand nr. 13","lat":46.771908,"lng":23.589451,"labeledLatLngs":[{"label":"display","lat":46.771908,"lng":23.589451}],"postalCode":"400110","cc":"RO","country":"Romania","contextLine":"","contextGeoId":-497622713,"formattedAddress":["<span itemprop=\"streetAddress\">Str. Regele Ferdinand nr. 13<\/span>","<span itemprop=\"postalCode\">400110<\/span>"]},"canonicalUrl":"https:\/\/foursquare.com\/v\/temaki--japanese-street-food\/589b75ac18fd2b5565de258b","canonicalPath":"\/v\/temaki--japanese-street-food\/589b75ac18fd2b5565de258b","categories":[{"id":"4bf58dd8d48988d1d2941735","name":"Sushi Restaurant","pluralName":"Sushi Restaurants","shortName":"Sushi","icon":{"prefix":"https:\/\/ss3.4sqi.net\/img\/categories_v2\/food\/sushi_","mapPrefix":"https:\/\/ss3.4sqi.net\/img\/categories_map\/food\/sushi","suffix":".png"},"primary":true}],"verified":false,"stats":{"tipCount":2,"usersCount":15,"checkinsCount":18,"visitsCount":21},"price":{"tier":2,"message":"Moderate","currency":"$"},"likes":{"count":0,"groups":[]},"like":false,"dislike":false,"ok":false,"allowMenuUrlEdit":true,"beenHere":{"count":0,"unconfirmedCount":0,"marked":false,"lastCheckinExpiredAt":0},"specials":{"count":0,"items":[]},"photos":{"count":3,"groups":[{"type":"venue","name":"Venue photos","count":3,"items":[{"id":"5909a86b2955131765009ca1","createdAt":1493805163,"source":{"name":"Swarm for iOS","url":"https:\/\/www.swarmapp.com"},"prefix":"https:\/\/fastly.4sqi.net\/img\/general\/","suffix":"\/82258667_ZNluGwwVwL1BAtOpz7O-ZWg1d6svpTIqa__HWfxFGyE.jpg","width":1440,"height":1920,"user":{"id":"82258667","firstName":"Mihai","lastName":"Serban","gender":"male","countryCode":"RO","canonicalUrl":"https:\/\/foursquare.com\/user\/82258667","canonicalPath":"\/user\/82258667","photo":{"prefix":"https:\/\/fastly.4sqi.net\/img\/user\/","suffix":"\/82258667-2IP0EE1JZCGIEMKU.jpg"},"isAnonymous":false},"visibility":"public"},{"id":"58a6ced219b1ad18d7871e1d","createdAt":1487326930,"source":{"name":"Swarm for iOS","url":"https:\/\/www.swarmapp.com"},"prefix":"https:\/\/fastly.4sqi.net\/img\/general\/","suffix":"\/82258667_tEnOo8T88NETtqu7a9eEMU6OdY2J_e4wzUvjqKjm_Og.jpg","width":1440,"height":1920,"user":{"id":"82258667","firstName":"Mihai","lastName":"Serban","gender":"male","countryCode":"RO","canonicalUrl":"https:\/\/foursquare.com\/user\/82258667","canonicalPath":"\/user\/82258667","photo":{"prefix":"https:\/\/fastly.4sqi.net\/img\/user\/","suffix":"\/82258667-2IP0EE1JZCGIEMKU.jpg"},"isAnonymous":false},"visibility":"public"},{"id":"58a438af1d21ba7074851a90","createdAt":1487157423,"source":{"name":"Swarm for Android","url":"https:\/\/www.swarmapp.com"},"prefix":"https:\/\/fastly.4sqi.net\/img\/general\/","suffix":"\/5797122_ukNuDX9U-XDmbegMvCFae_TCzBUdjfodNDSwv0lBalA.jpg","width":3036,"height":4048,"user":{"id":"5797122","firstName":"Ioana 🚲✈🚀","lastName":"Chiorean","gender":"female","countryCode":"RO","canonicalUrl":"https:\/\/foursquare.com\/user\/5797122","canonicalPath":"\/ioana_cis","photo":{"prefix":"https:\/\/fastly.4sqi.net\/img\/user\/","suffix":"\/5797122-2DTIKGRFSEZSI0H5.jpg"},"isAnonymous":false},"visibility":"public"}]}]},"reasons":{"count":0,"items":[]},"description":"Temaki is a small place where you can taste various Japanese street food like Temaki, Sushi Burrito, and FruitCorn. Also, you can taste the special Japanese tea and enjoy traditional Japanese music.","hereNow":{"count":0,"summary":"Nobody here","groups":[]},"createdAt":1486583212,"tips":{"count":2,"groups":[{"type":"following","name":"Tips from people you follow","count":0,"items":[]},{"type":"others","name":"All tips","count":2,"items":[{"id":"59826a604382ab1ec476d3d9","createdAt":1501719136,"text":"I'm a sushi fan, but with sushi burrito, it was my first experience. The food was very tasty and good, done with fresh products and served with love. Recommend to everybody!!!","type":"user","canonicalUrl":"https:\/\/foursquare.com\/item\/59826a604382ab1ec476d3d9","canonicalPath":"\/item\/59826a604382ab1ec476d3d9","likes":{"count":0,"groups":[]},"like":false,"logView":true,"agreeCount":0,"disagreeCount":0,"todo":{"count":0},"user":{"id":"394829648","firstName":"Yuri","gender":"male","countryCode":"IT","canonicalUrl":"https:\/\/foursquare.com\/user\/394829648","canonicalPath":"\/user\/394829648","photo":{"prefix":"https:\/\/fastly.4sqi.net\/img\/user\/","suffix":"\/394829648_zu0vLcNw_RactvSv5-rUJNPZB8cVwyF_4g5Q-dizk9rcxIFammWBIIrKfnEqfG3xx-PRi37Dr.jpg"},"isAnonymous":false}},{"id":"59822fed35f9837227873590","createdAt":1501704173,"text":"It is a pleasant and calm place, with good food, fast serving and a decent price. Recomand this place","type":"user","canonicalUrl":"https:\/\/foursquare.com\/item\/59822fed35f9837227873590","canonicalPath":"\/item\/59822fed35f9837227873590","likes":{"count":0,"groups":[]},"like":false,"logView":true,"agreeCount":1,"disagreeCount":0,"todo":{"count":0},"user":{"id":"437125375","firstName":"Igor","lastName":"C","gender":"male","countryCode":"RO","canonicalUrl":"https:\/\/foursquare.com\/user\/437125375","canonicalPath":"\/user\/437125375","photo":{"prefix":"https:\/\/fastly.4sqi.net\/img\/user\/","suffix":"\/blank_boy.png","default":true},"isAnonymous":false}}]}]},"shortUrl":"http:\/\/4sq.com\/2llf1PW","timeZone":"Europe\/Bucharest","listed":{"count":0,"groups":[]},"phrases":[{"phrase":"sushi burrito","sample":{"entities":[{"indices":[26,39],"type":"keyPhrase","url":"\/explore?q=sushi+burrito&near="}],"text":"... a sushi fan, but with sushi burrito, it was my first experience. The food was..."},"count":1}],"hours":{"status":"Open until 10:00 PM","richStatus":{"entities":[],"text":"Open until 10:00 PM"},"isOpen":true,"isLocalHoliday":false,"dayData":[],"timeframes":[{"days":"Mon\u2013Fri","includesToday":true,"open":[{"renderedTime":"10:00 AM\u201310:00 PM"}],"segments":[]}]},"seasonalHours":[],"defaultHours":{"status":"Open until 10:00 PM","richStatus":{"entities":[],"text":"Open until 10:00 PM"},"isOpen":true,"isLocalHoliday":false,"dayData":[],"timeframes":[{"days":"Mon\u2013Fri","includesToday":true,"open":[{"renderedTime":"10:00 AM\u201310:00 PM"}],"segments":[]}]},"pageUpdates":{"count":0,"items":[]},"structuredLocation":[{"cc":"RO","name":"","woeType":22,"longId":"9151314444285984048","allowExplore":true},{"cc":"RO","name":"","woeType":22,"longId":"-366883263","allowExplore":true},{"cc":"RO","name":"","woeType":22,"longId":"-928100363","allowExplore":true},{"name":"RO","woeType":12,"longId":"72057594038726485","allowExplore":true}],"permissions":{"addTips":true,"showPhotos":true,"flagTips":true,"editHours":true,"editVenue":false,"seeEditVenuePage":false,"editCategories":true,"viewEditHistory":false,"viewGeoAdminPage":false,"viewShapesAdminPage":false,"viewSubvenueEditorAdminPage":false,"viewEventsAdminPage":false,"flagVenue":true,"viewFlags":false,"hasRestrictedAddress":false,"indexable":true,"isCreator":false,"sendUpdates":false,"canEditAttributes":true,"usesState":false,"usesAddress":true,"usesPhone":true,"canRollbackEdits":false},"inbox":{"count":0,"items":[]},"venueChains":[],"attributes":{"groups":[{"type":"price","name":"Price","summary":"$$","count":1,"items":[{"displayName":"Price","displayValue":"$$","priceTier":2}]}]},"bestPhoto":{"id":"5909a86b2955131765009ca1","createdAt":1493805163,"source":{"name":"Swarm for iOS","url":"https:\/\/www.swarmapp.com"},"prefix":"https:\/\/fastly.4sqi.net\/img\/general\/","suffix":"\/82258667_ZNluGwwVwL1BAtOpz7O-ZWg1d6svpTIqa__HWfxFGyE.jpg","width":1440,"height":1920,"visibility":"public"},"colors":{"highlightColor":{"photoId":"5909a86b2955131765009ca1","value":-9936816},"highlightTextColor":{"photoId":"5909a86b2955131765009ca1","value":-1},"algoVersion":3},"aliases":["temaki  japanese street food","temaki - japanese street food","temaki -japanese street food","temaki japanese street food"],"metaTags":{"description":"See 3 photos and 2 tips from 12 visitors to Temaki - Japanese Street Food. \"I'm a sushi fan, but with sushi burrito, it was my first experience. The...\"","title":"Temaki - Japanese Street Food - Sushi Restaurant"}},"pageConfig":{"hideTastepile":true,"showSeeAllTipsButton":true,"tipCountMax":5}}}
